python_sharp.py
python_sharp-1.2.1.dist-info/licenses/LICENSE
python_sharp-1.2.1.dist-info/METADATA
python_sharp-1.2.1.dist-info/WHEEL
python_sharp-1.2.1.dist-info/top_level.txt
python_sharp-1.2.1.dist-info/RECORD
