Metadata-Version: 2.4
Name: python_sharp
Version: 1.2.1
Summary: python# (python sharp) is a module created to add EOP (event oriented programing) into python in the most native feeling, easy sintax way possible. Based on C# event implementation structure
Home-page: https://github.com/juanclopgar97/python_sharp.git
Author: Juan Carlos Lopez Garcia
Author-email: juanclopgar@gmail.com
Keywords: event oriented programming,EOP,event-driven,Python events,delegates,@event,callback management,C# inspired,Python decorators,event,events,easy
Classifier: Programming Language :: Python :: 3
Classifier: License :: OSI Approved :: MIT License
Classifier: Operating System :: OS Independent
Requires-Python: >=3.6
License-File: LICENSE
Dynamic: author
Dynamic: author-email
Dynamic: classifier
Dynamic: description
Dynamic: description-content-type
Dynamic: home-page
Dynamic: keywords
Dynamic: license-file
Dynamic: requires-python
Dynamic: summary
